tests/__init__.py
tests/spider_test.py
twitter_spider/__init__.py
twitter_spider/twitter_spider.py
twitter_spider-0.2.dist-info/LICENSE
twitter_spider-0.2.dist-info/METADATA
twitter_spider-0.2.dist-info/WHEEL
twitter_spider-0.2.dist-info/top_level.txt
twitter_spider-0.2.dist-info/RECORD
